quota-coalesced-stream-arbitration/rtl/stream_arbiter.sv
`default_nettype none
// Independent ready/valid beats; this is not a packet or AXI arbiter.
module stream_arbiter #(
    parameter integer N=4,
    parameter integer WIDTH=16,
    parameter integer QUOTA=4,
    parameter integer FIXED=0,
    parameter integer IW=(N<=1 ? 1 : $clog2(N))
) (
    input wire clk, rst,
    input wire [N-1:0] s_valid,
    input wire [N*WIDTH-1:0] s_data,
    output reg [N-1:0] s_ready,
    output reg m_valid,
    output reg [WIDTH-1:0] m_data,
    output reg [IW-1:0] m_source,
    input wire m_ready
);
    localparam CW=(QUOTA<=1 ? 1 : $clog2(QUOTA));
    reg [IW-1:0] pointer, owner, lock_owner;
    reg [CW-1:0] remaining;
    reg locked;
    reg [IW-1:0] first_any, first_masked, selected;
    reg found_any, found_masked;
    integer i;
    // Two parallel priority searches implement cyclic masked selection.
    always @* begin
        first_any=0; first_masked=0; found_any=0; found_masked=0;
        for (i=0; i<N; i=i+1) begin
            if (s_valid[i] && !found_any) begin
                first_any=i; found_any=1;
            end
            if (s_valid[i] && i>=pointer && !found_masked) begin
                first_masked=i; found_masked=1;
            end
        end
        selected=FIXED ? first_any : (found_masked ? first_masked : first_any);
        if (!FIXED && QUOTA>1 && remaining!=0 && s_valid[owner]) selected=owner;
        if (locked) selected=lock_owner;
        m_valid=0; m_data=0; m_source=0; s_ready=0;
        if (!rst && found_any) begin
            m_valid=1;
            m_source=selected;
            m_data=s_data[selected*WIDTH +: WIDTH];
            s_ready[selected]=m_ready;
        end
    end
    always @(posedge clk) begin
        if (rst) begin
            pointer<=0; owner<=0; remaining<=0; locked<=0; lock_owner<=0;
        end else begin
            // Capture selection while blocked, including late arrivals.
            locked<=m_valid && !m_ready;
            if (m_valid && !m_ready) lock_owner<=selected;
            // An idle interval expires a partial quota but preserves scan history.
            if (!found_any) remaining<=0;
            if (m_valid && m_ready) begin
                pointer <= (selected==N-1) ? 0 : selected+1'b1;
                owner <= selected;
                if (remaining!=0 && owner==selected) remaining<=remaining-1'b1;
                else remaining<=QUOTA-1;
            end
        end
    end
endmodule
`default_nettype wire

quota-coalesced-stream-arbitration/tb/check_vectors.sv
`default_nettype none
module tb;
    localparam N=`N, WIDTH=`WIDTH, Q=`QUOTA, FIXED=`FIXED;
    localparam IW=(N<=1 ? 1 : $clog2(N));
    reg clk=0;
    always #5 clk=~clk;
    reg rst=1, m_ready=0;
    reg [N-1:0] s_valid=0;
    reg [N*WIDTH-1:0] s_data=0;
    wire [N-1:0] s_ready;
    wire m_valid;
    wire [WIDTH-1:0] m_data;
    wire [IW-1:0] m_source;
`ifdef POST_SYNTH
    stream_arbiter dut(.*);
`else
    stream_arbiter #(.N(N),.WIDTH(WIDTH),.QUOTA(Q),.FIXED(FIXED)) dut(.*);
`endif
    integer fd, status, row=0, fires=0, stalls=0, i, warmup=512;
    integer eval_fires=0, switches=0, last_source=-1, max_wait=0;
    integer waits [0:N-1];
    integer services [0:N-1];
    integer vr, mr, ev, es;
    reg [N-1:0] req, er;
    reg [N*WIDTH-1:0] data_in;
    reg [WIDTH-1:0] ed;
    reg previous_stall=0, previous_reset=1;
    reg [WIDTH-1:0] previous_data;
    reg [IW-1:0] previous_source;
    reg [N-1:0] previous_valid, previous_ready;
    reg [N*WIDTH-1:0] previous_input;
    reg [2047:0] filename;
    initial begin
        status=$value$plusargs("WARMUP=%d",warmup);
        for (i=0;i<N;i=i+1) begin waits[i]=0;services[i]=0;end
        if (!$value$plusargs("VECTORS=%s",filename)) $fatal(1,"missing vectors");
        fd=$fopen(filename,"r");
        if (!fd) $fatal(1,"cannot read vectors");
        if ($test$plusargs("WAVE")) begin $dumpfile("wave.vcd"); $dumpvars(0,tb); end
        while (!$feof(fd)) begin
            status=$fscanf(fd,"%d %d %h %h %d %d %h %h\n",vr,mr,req,data_in,ev,es,er,ed);
            if (status!=8) $fatal(1,"invalid vector row %0d",row);
            @(negedge clk);
            rst=vr; m_ready=mr; s_valid=req; s_data=data_in;
            @(posedge clk);
            // Sample before sequential state updates, exactly at the handshake edge.
            if (m_valid!==ev[0] || s_ready!==er ||
                (ev && (m_data!==ed || m_source!==es[IW-1:0])))
                $fatal(1,"scoreboard mismatch row=%0d got=%b,%0d,%h,%h expected=%0d,%0d,%h,%h",
                    row,m_valid,m_source,s_ready,m_data,ev,es,er,ed);
            if ((s_ready & (s_ready-1'b1))!=0 || (s_ready & ~s_valid)!=0)
                $fatal(1,"grant conservation failed");
            if (!rst && previous_stall && !previous_reset) begin
                if (!m_valid || m_data!==previous_data || m_source!==previous_source)
                    $fatal(1,"output changed under backpressure");
            end
            for (i=0;i<N;i=i+1) begin
                if (!rst && !previous_reset && previous_valid[i] && !previous_ready[i])
                    if (!s_valid[i] || s_data[i*WIDTH +: WIDTH]!==previous_input[i*WIDTH +: WIDTH])
                        $fatal(1,"illegal source stimulus on port %0d row %0d",i,row);
            end
            if (m_valid && m_ready) fires=fires+1;
            if (m_valid && !m_ready) stalls=stalls+1;
            if (rst) last_source=-1;
            for (i=0;i<N;i=i+1) begin
                if (rst || !s_valid[i]) waits[i]=0;
                else if (m_valid && m_ready) begin
                    if (m_source==i) begin
                        if (row>=warmup) begin
                            services[i]=services[i]+1;
                            if (waits[i]>max_wait) max_wait=waits[i];
                        end
                        waits[i]=0;
                    end else waits[i]=waits[i]+1;
                end
            end
            if (row>=warmup && m_valid && m_ready) begin
                eval_fires=eval_fires+1;
                if (last_source>=0 && last_source!=m_source) switches=switches+1;
                last_source=m_source;
            end
            previous_stall=m_valid && !m_ready; previous_data=m_data; previous_source=m_source;
            previous_reset=rst; previous_valid=s_valid; previous_ready=s_ready; previous_input=s_data;
            row=row+1;
        end
        $fclose(fd);
        $display("PASS cycles=%0d fires=%0d stalls=%0d eval_fires=%0d switches=%0d wait_max=%0d",row,fires,stalls,eval_fires,switches,max_wait);
        $write("SERVICE");
        for (i=0;i<N;i=i+1) $write(" %0d",services[i]);
        $write("\n");
        $finish;
    end
endmodule
`default_nettype wire

quota-coalesced-stream-arbitration/results/protocol.vcd
$date
	Wed Oct  7 14:18:54 2026
$end
$version
	Icarus Verilog
$end
$timescale
	1s
$end
$scope module tb $end
$var wire 4 ! s_ready [3:0] $end
$var wire 1 " m_valid $end
$var wire 2 # m_source [1:0] $end
$var wire 16 $ m_data [15:0] $end
$var parameter 32 % FIXED $end
$var parameter 32 & IW $end
$var parameter 32 ' N $end
$var parameter 32 ( Q $end
$var parameter 32 ) WIDTH $end
$var reg 1 * clk $end
$var reg 64 + data_in [63:0] $end
$var reg 16 , ed [15:0] $end
$var reg 4 - er [3:0] $end
$var reg 2048 . filename [2047:0] $end
$var reg 1 / m_ready $end
$var reg 16 0 previous_data [15:0] $end
$var reg 64 1 previous_input [63:0] $end
$var reg 4 2 previous_ready [3:0] $end
$var reg 1 3 previous_reset $end
$var reg 2 4 previous_source [1:0] $end
$var reg 1 5 previous_stall $end
$var reg 4 6 previous_valid [3:0] $end
$var reg 4 7 req [3:0] $end
$var reg 1 8 rst $end
$var reg 64 9 s_data [63:0] $end
$var reg 4 : s_valid [3:0] $end
$var integer 32 ; es [31:0] $end
$var integer 32 < ev [31:0] $end
$var integer 32 = eval_fires [31:0] $end
$var integer 32 > fd [31:0] $end
$var integer 32 ? fires [31:0] $end
$var integer 32 @ i [31:0] $end
$var integer 32 A last_source [31:0] $end
$var integer 32 B max_wait [31:0] $end
$var integer 32 C mr [31:0] $end
$var integer 32 D row [31:0] $end
$var integer 32 E stalls [31:0] $end
$var integer 32 F status [31:0] $end
$var integer 32 G switches [31:0] $end
$var integer 32 H vr [31:0] $end
$var integer 32 I warmup [31:0] $end
$scope module dut $end
$var wire 1 * clk $end
$var wire 1 / m_ready $end
$var wire 1 8 rst $end
$var wire 64 J s_data [63:0] $end
$var wire 4 K s_valid [3:0] $end
$var parameter 32 L CW $end
$var parameter 32 M FIXED $end
$var parameter 32 N IW $end
$var parameter 32 O N $end
$var parameter 32 P QUOTA $end
$var parameter 32 Q WIDTH $end
$var reg 2 R first_any [1:0] $end
$var reg 2 S first_masked [1:0] $end
$var reg 1 T found_any $end
$var reg 1 U found_masked $end
$var reg 2 V lock_owner [1:0] $end
$var reg 1 W locked $end
$var reg 16 X m_data [15:0] $end
$var reg 2 Y m_source [1:0] $end
$var reg 1 " m_valid $end
$var reg 2 Z owner [1:0] $end
$var reg 2 [ pointer [1:0] $end
$var reg 2 \ remaining [1:0] $end
$var reg 4 ] s_ready [3:0] $end
$var reg 2 ^ selected [1:0] $end
$var integer 32 _ i [31:0] $end
$upscope $end
$upscope $end
$enddefinitions $end
$comment Show the parameter values. $end
$dumpall
b10000 Q
b100 P
b100 O
b10 N
b0 M
b10 L
b10000 )
b100 (
b100 '
b10 &
b0 %
$end
#0
$dumpvars
bx _
bx ^
bx ]
bx \
bx [
bx Z
bx Y
bx X
xW
bx V
xU
xT
bx S
bx R
b0 K
b0 J
b0 I
b1 H
b0 G
b1000 F
b0 E
b0 D
b1 C
b0 B
b11111111111111111111111111111111 A
b100 @
b0 ?
b10000000000000000000000000000011 >
b0 =
b0 <
b0 ;
b0 :
b0 9
18
b0 7
bx 6
05
bx 4
13
bx 2
bx 1
bx 0
0/
b101111011101110110111101110010011010110111001101110000011000010110001101100101001011110110001101101111011011010111000001110101011101000110010101110010001011010110000101110010011000110110100001101001011101000110010101100011011101000111010101110010011001010010110101110010011001010111001101100101011000010111001001100011011010000010111101110001011101010110111101110100011000010010110101100011011011110110000101101100011001010111001101100011011001010110010000101101011100110111010001110010011001010110000101101101001011010110000101110010011000100110100101110100011100100110000101110100011010010110111101101110001011110110001001110101011010010110110001100100001011110111011001100101011000110111010001101111011100100111001100101110011101000111100001110100 .
b0 -
b0 ,
b0 +
0*
bx $
bx #
x"
bx !
$end
#5
b0 !
b0 ]
b0 #
b0 Y
b0 $
b0 X
0"
b0 ^
b100 _
0U
0T
b0 S
b0 R
b0 V
0W
b0 \
b0 Z
b0 [
1*
#10
b100 _
1/
0*
#15
b1 D
b0 1
b0 2
b0 6
b0 4
b0 0
b100 @
1*
#20
0*
#25
b111000101 ,
b11 ;
b1 <
b111000101000000000000000000000000000000000000000000000000 +
b1000 7
b0 C
b0 H
b10 D
b100 @
1*
#30
b111000101 $
b111000101 X
b11 #
b11 Y
1"
b11 ^
1U
b11 S
1T
b11 R
b100 _
b111000101000000000000000000000000000000000000000000000000 9
b111000101000000000000000000000000000000000000000000000000 J
b1000 :
b1000 K
0/
08
0*
#35
b11 #
b11 Y
b111000101 $
b111000101 X
1"
b100 _
1U
1T
b11 S
b11 R
b11 V
1W
b11 D
b111000101000000000000000000000000000000000000000000000000 1
b1000 6
03
b11 4
b111000101 0
15
b1 E
b100 @
1*
#40
0*
#45
b1001 7
b100 D
b10 E
b100 @
1*
#50
b11 #
b11 Y
b111000101 $
b111000101 X
1"
b11 ^
b100 _
1U
1T
b0 S
b0 R
b1001 :
b1001 K
0*
#55
b101 D
b1001 6
b11 E
b100 @
1*
#60
0*
#65
b111000101000000010010111000000000100101110000000000000000 +
b1111 7
b110 D
b100 E
b100 @
1*
#70
b11 #
b11 Y
b111000101 $
b111000101 X
1"
b11 ^
b100 _
1U
1T
b111000101000000010010111000000000100101110000000000000000 9
b111000101000000010010111000000000100101110000000000000000 J
b1111 :
b1111 K
0*
#75
b111 D
b111000101000000010010111000000000100101110000000000000000 1
b1111 6
b101 E
b100 @
1*
#80
0*
#85
b1000 D
b110 E
b100 @
1*
#90
0*
#95
b1001 D
b111 E
b100 @
1*
#100
0*
#105
b1000 -
b1 C
b1010 D
b1000 E
b100 @
1*
#110
b1000 !
b1000 ]
b11 #
b11 Y
b111000101 $
b111000101 X
1"
b11 ^
b100 _
1U
1T
1/
0*
#115
b1000 !
b1000 ]
b11 #
b11 Y
b111000101 $
b111000101 X
1"
b11 ^
b100 _
1U
1T
b11 \
b11 Z
0W
b110001100 ,
b110001100000000010010111000000000100101110000000000000000 +
b1011 D
b1000 2
05
b11 A
b1 =
b1 ?
b100 @
1*
#120
b1000 !
b1000 ]
b11 #
b11 Y
b110001100 $
b110001100 X
1"
b11 ^
b100 _
1U
1T
b110001100000000010010111000000000100101110000000000000000 9
b110001100000000010010111000000000100101110000000000000000 J
0*
#125
b1000 !
b1000 ]
b11 #
b11 Y
b110001100 $
b110001100 X
1"
b11 ^
b100 _
1U
1T
b10 \
b0 ,
b1 -
b0 ;
b10010111000000000100101110000000000000000 +
b111 7
b1100 D
b110001100000000010010111000000000100101110000000000000000 1
b110001100 0
b10 =
b10 ?
b100 @
1*
#130
b1 !
b1 ]
b0 #
b0 Y
b0 $
b0 X
1"
b0 ^
b100 _
1U
1T
b10010111000000000100101110000000000000000 9
b10010111000000000100101110000000000000000 J
b111 :
b111 K
0*
#135
b1 !
b1 ]
1"
b0 ^
b1 S
b100 _
1U
1T
b11 \
b0 Z
b1 [
b1001001 ,
b10010111000000000100101110000000001001001 +
b1101 D
b10010111000000000100101110000000000000000 1
b1 2
b111 6
b0 4
b0 0
b0 A
b1 G
b11 =
b10 B
b11 ?
b100 @
1*
#140
b1001001 $
b1001001 X
b1 !
b1 ]
1"
b0 ^
b100 _
1U
1T
b1 S
b10010111000000000100101110000000001001001 9
b10010111000000000100101110000000001001001 J
0*
#145
b1 !
b1 ]
b1001001 $
b1001001 X
1"
b0 ^
b100 _
1U
1T
b1 S
b10 \
b10010111 ,
b10 -
b1 ;
b10010111000000000100101110000000000000000 +
b110 7
b1110 D
b10010111000000000100101110000000001001001 1
b1001001 0
b100 =
b100 ?
b100 @
1*
#150
b1 #
b1 Y
b10 !
b10 ]
b10010111 $
b10010111 X
1"
b1 ^
b1 R
b100 _
1U
1T
b1 S
b10010111000000000100101110000000000000000 9
b10010111000000000100101110000000000000000 J
b110 :
b110 K
0*
#155
b10 !
b10 ]
b1 #
b1 Y
b10010111 $
b10010111 X
1"
b1 ^
b100 _
1U
1T
b10 S
b1 R
b11 \
b1 Z
b10 [
b100101110 ,
b100 -
b10 ;
b10010111000000000000000000000000000000000 +
b100 7
b1111 D
b10010111000000000100101110000000000000000 1
b10 2
b110 6
b1 4
b10010111 0
b1 A
b10 G
b101 =
b100 B
b101 ?
b100 @
1*
#160
b100 !
b100 ]
b10 #
b10 Y
b100101110 $
b100101110 X
1"
b10 ^
b100 _
1U
1T
b10 S
b10 R
b10010111000000000000000000000000000000000 9
b10010111000000000000000000000000000000000 J
b100 :
b100 K
0*
#165
b100 !
b100 ]
b10 #
b10 Y
b100101110 $
b100101110 X
1"
b100 _
0U
1T
b0 S
b10 R
b10 Z
b11 [
b0 ,
b0 -
b0 ;
b0 <
b0 +
b0 7
b10000 D
b10010111000000000000000000000000000000000 1
b100 2
b100 6
b10 4
b100101110 0
b10 A
b11 G
b110 =
b101 B
b110 ?
b100 @
1*
#170
b0 !
b0 ]
b0 #
b0 Y
b0 $
b0 X
0"
b0 ^
b100 _
0T
b0 R
b0 9
b0 J
b0 :
b0 K
0*
#175
b100 _
b0 \
b10001 D
b0 1
b0 2
b0 6
b0 4
b0 0
b100 @
1*
#180
0*
#185
b10010 D
b100 @
1*
#190
0*
#195
b10011 D
b100 @
1*
#200
0*
#205
b10100 D
b100 @
1*
#210
0*
#215
b10101 D
b100 @
1*
#220
0*
#225
b10110 D
b100 @
1*
#230
0*
#235
b10111 D
b100 @
1*
#240
0*
#245
b11000 D
b100 @
1*
#250
0*
#255
b11001 D
b100 @
1*
#260
0*
#265
b11010 D
b100 @
1*
#270
0*
#275
b11011 D
b100 @
1*
#280
0*
#285
b11100 D
b100 @
1*
#290
0*
#295
b11101 D
b100 @
1*
#300
0*
#305
b11110 D
b100 @
1*
#310
0*
#315
b11111 D
b100 @
1*
#320
0*
#325
b100000 D
b100 @
1*
#330
0*
#335
b100001 D
b100 @
1*
#340
0*
#345
b100010 D
b100 @
1*
#350
0*
#355
b100011 D
b100 @
1*
#360
0*
#365
b100100 D
b100 @
1*
#370
0*
#375
b100101 D
b100 @
1*
#380
0*
#385
b100110 D
b100 @
1*
#390
0*
#395
b100111 D
b100 @
1*
#400
0*
#405
b101000 D
b100 @
1*
#410
0*
#415
b101001 D
b100 @
1*
#420
0*
#425
b101010 D
b100 @
1*
#430
0*
#435
b101011 D
b100 @
1*
#440
0*
#445
b101100 D
b100 @
1*
#450
0*
#455
b101101 D
b100 @
1*
#460
0*
#465
b101110 D
b100 @
1*
#470
0*
#475
b101111 D
b100 @
1*
#480
0*
#485
b110000 D
b100 @
1*
#490
0*
#495
b110001 D
b100 @
1*
#500
0*
#505
b110010 D
b100 @
1*
#510
0*
#515
b110011 D
b100 @
1*
#520
0*
#525
b110100 D
b100 @
1*
#530
0*
#535
b110101 D
b100 @
1*
#540
0*
#545
b110110 D
b100 @
1*
#550
0*
#555
b110111 D
b100 @
1*
#560
0*
#565
b111000 D
b100 @
1*
#570
0*
#575
b111001 D
b100 @
1*
#580
0*
#585
b111010 D
b100 @
1*
#590
0*
#595
b111011 D
b100 @
1*
#600
0*
#605
b101010111 ,
b11 ;
b1 <
b101010111000000010110011100000000110111100000000010010010 +
b1111 7
b0 C
b111100 D
b100 @
1*
#610
b101010111 $
b101010111 X
b11 #
b11 Y
1"
b11 ^
1U
b11 S
1T
b100 _
b101010111000000010110011100000000110111100000000010010010 9
b101010111000000010110011100000000110111100000000010010010 J
b1111 :
b1111 K
0/
0*
#615
b11 #
b11 Y
b101010111 $
b101010111 X
1"
b100 _
1U
1T
b11 S
1W
b111101 D
b101010111000000010110011100000000110111100000000010010010 1
b1111 6
b11 4
b101010111 0
15
b1001 E
b100 @
1*
#620
0*
#625
b111110 D
b1010 E
b100 @
1*
#630
0*
#635
b111111 D
b1011 E
b100 @
1*
#640
0*
#645
b1000000 D
b1100 E
b100 @
1*
#650
0*
#655
b1000001 D
b1101 E
b100 @
1*
#660
0*
#665
b1000010 D
b1110 E
b100 @
1*
#670
0*
#675
b1000011 D
b1111 E
b100 @
1*
#680
0*
#685
b1000100 D
b10000 E
b100 @
1*
#690
0*
#695
b1000101 D
b10001 E
b100 @
1*
#700
0*
#705
b0 ,
b0 ;
b0 <
b0 +
b0 7
b1 H
b1000110 D
b10010 E
b100 @
1*
#710
b0 #
b0 Y
b0 $
b0 X
0"
b11 ^
b100 _
0U
0T
b0 S
b0 9
b0 J
b0 :
b0 K
18
0*
#715
b0 ^
b100 _
b0 V
0W
b0 Z
b0 [
b1000111 D
b0 1
b0 6
13
b0 4
b0 0
05
b11111111111111111111111111111111 A
b100 @
1*
#720
0*
#725
b0 H
b1001000 D
b100 @
1*
#730
b100 _
08
0*
#735
b1001001 D
03
b100 @
1*
#740
0*
#745
b1001010 D
b100 @
1*
#750
0*
#755
b1001011 D
b100 @
1*
#760
0*
#765
b1 C
b1001100 D
b100 @
1*
#770
b100 _
1/
0*
#775
b1001101 D
b100 @
1*
#780
0*
#785
b1001110 D
b100 @
1*
#790
0*
#795
b1001111 D
b100 @
1*
#800
0*
#805
b110110110 ,
b1 -
b1 <
b1110011000000000100001100000001111110100000000110110110 +
b1111 7
b1010000 D
b100 @
1*
#810
b1 !
b1 ]
b110110110 $
b110110110 X
1"
1U
1T
b100 _
b1110011000000000100001100000001111110100000000110110110 9
b1110011000000000100001100000001111110100000000110110110 J
b1111 :
b1111 K
0*
#815
b1 !
b1 ]
b110110110 $
b110110110 X
1"
b0 ^
b1 S
b100 _
1U
1T
b11 \
b1 [
b111111111 ,
b1110011000000000100001100000001111110100000000111111111 +
b1010001 D
b1110011000000000100001100000001111110100000000110110110 1
b1 2
b1111 6
b110110110 0
b0 A
b111 =
b111 ?
b100 @
1*
#820
b1 !
b1 ]
b111111111 $
b111111111 X
1"
b0 ^
b100 _
1U
1T
b1 S
b1110011000000000100001100000001111110100000000111111111 9
b1110011000000000100001100000001111110100000000111111111 J
0*
#825
b1 !
b1 ]
b111111111 $
b111111111 X
1"
b0 ^
b100 _
1U
1T
b1 S
b10 \
b111111010 ,
b10 -
b1 ;
b1110011000000000100001100000001111110100000000000000000 +
b1110 7
b1010010 D
b1110011000000000100001100000001111110100000000111111111 1
b111111111 0
b1000 =
b1000 ?
b100 @
1*
#830
b1 #
b1 Y
b10 !
b10 ]
b111111010 $
b111111010 X
1"
b1 ^
b1 R
b100 _
1U
1T
b1 S
b1110011000000000100001100000001111110100000000000000000 9
b1110011000000000100001100000001111110100000000000000000 J
b1110 :
b1110 K
0*
#835
b10 !
b10 ]
b1 #
b1 Y
b111111010 $
b111111010 X
1"
b1 ^
b100 _
1U
1T
b10 S
b1 R
b11 \
b1 Z
b10 [
b100100001 ,
b1110011000000000100001100000001001000010000000000000000 +
b1010011 D
b1110011000000000100001100000001111110100000000000000000 1
b10 2
b1110 6
b1 4
b111111010 0
b1 A
b100 G
b1001 =
b1001 ?
b100 @
1*
#840
b10 !
b10 ]
b1 #
b1 Y
b100100001 $
b100100001 X
1"
b1 ^
b100 _
1U
1T
b10 S
b1 R
b1110011000000000100001100000001001000010000000000000000 9
b1110011000000000100001100000001001000010000000000000000 J
0*
#845
b10 !
b10 ]
b1 #
b1 Y
b100100001 $
b100100001 X
1"
b1 ^
b100 _
1U
1T
b10 S
b1 R
b10 \
b1000011 ,
b100 -
b10 ;
b1110011000000000100001100000000000000000000000000000000 +
b1100 7
b1010100 D
b1110011000000000100001100000001001000010000000000000000 1
b100100001 0
b1010 =
b1010 ?
b100 @
1*
#850
b100 !
b100 ]
b10 #
b10 Y
b1000011 $
b1000011 X
1"
b10 ^
b100 _
1U
1T
b10 S
b10 R
b1110011000000000100001100000000000000000000000000000000 9
b1110011000000000100001100000000000000000000000000000000 J
b1100 :
b1100 K
0*
#855
b100 !
b100 ]
b10 #
b10 Y
b1000011 $
b1000011 X
1"
b10 ^
b100 _
1U
1T
b11 S
b10 R
b11 \
b10 Z
b11 [
b10011000 ,
b1110011000000001001100000000000000000000000000000000000 +
b1010101 D
b1110011000000000100001100000000000000000000000000000000 1
b100 2
b1100 6
b10 4
b1000011 0
b10 A
b101 G
b1011 =
b1011 ?
b100 @
1*
#860
b100 !
b100 ]
b10 #
b10 Y
b10011000 $
b10011000 X
1"
b10 ^
b100 _
1U
1T
b11 S
b10 R
b1110011000000001001100000000000000000000000000000000000 9
b1110011000000001001100000000000000000000000000000000000 J
0*
#865
b100 !
b100 ]
b10 #
b10 Y
b10011000 $
b10011000 X
1"
b10 ^
b100 _
1U
1T
b11 S
b10 R
b10 \
b1110011 ,
b1000 -
b11 ;
b1110011000000000000000000000000000000000000000000000000 +
b1000 7
b1010110 D
b1110011000000001001100000000000000000000000000000000000 1
b10011000 0
b1100 =
b1100 ?
b100 @
1*
#870
b1000 !
b1000 ]
b11 #
b11 Y
b1110011 $
b1110011 X
1"
b11 ^
b100 _
1U
1T
b11 S
b11 R
b1110011000000000000000000000000000000000000000000000000 9
b1110011000000000000000000000000000000000000000000000000 J
b1000 :
b1000 K
0*
#875
b1000 !
b1000 ]
b11 #
b11 Y
b1110011 $
b1110011 X
1"
b100 _
1U
1T
b11 S
b11 R
b11 \
b11 Z
b0 [
b111010 ,
b111010000000000000000000000000000000000000000000000000 +
b1010111 D
b1110011000000000000000000000000000000000000000000000000 1
b1000 2
b1000 6
b11 4
b1110011 0
b11 A
b110 G
b1101 =
b110 B
b1101 ?
b100 @
1*
#880
b1000 !
b1000 ]
b11 #
b11 Y
b111010 $
b111010 X
1"
b100 _
1U
1T
b11 S
b11 R
b111010000000000000000000000000000000000000000000000000 9
b111010000000000000000000000000000000000000000000000000 J
0*
#885
b1000 !
b1000 ]
b11 #
b11 Y
b111010 $
b111010 X
1"
b100 _
1U
1T
b11 S
b11 R
b10 \
b0 ,
b0 -
b0 ;
b0 <
b0 +
b0 7
b1011000 D
b111010000000000000000000000000000000000000000000000000 1
b111010 0
b1110 =
b1110 ?
b100 @
1*
#890
b0 !
b0 ]
b0 #
b0 Y
b0 $
b0 X
0"
b0 ^
b100 _
0U
0T
b0 S
b0 R
b0 9
b0 J
b0 :
b0 K
0*
#895
b100 _
b0 \
b1011001 D
b0 1
b0 2
b0 6
b0 4
b0 0
b100 @
1*
#900
0*
#905
b1011010 D
b100 @
1*
#910
0*
#915
b1011011 D
b100 @
1*
#920
0*
#925
b1011100 D
b100 @
1*
#930
0*
#935
b1011101 D
b100 @
1*
#940
0*
#945
b1011110 D
b100 @
1*
#950
0*
#955
b1011111 D
b100 @
1*
#960
0*
#965
b1100000 D
b100 @
1*
#970
0*
#975
b1100001 D
b100 @
1*
#980
0*
#985
b1100010 D
b100 @
1*
#990
0*
#995
b1100011 D
b100 @
1*
#1000
0*
#1005
b1100100 D
b100 @
1*
#1010
0*
#1015
b1100101 D
b100 @
1*
#1020
0*
#1025
b1100110 D
b100 @
1*
#1030
0*
#1035
b1100111 D
b100 @
1*
#1040
0*
#1045
b1101000 D
b100 @
1*
#1050
0*
#1055
b1101001 D
b100 @
1*
#1060
0*
#1065
b1101010 D
b100 @
1*
#1070
0*
#1075
b1101011 D
b100 @
1*
#1080
0*
#1085
b1101100 D
b100 @
1*
#1090
0*
#1095
b1101101 D
b100 @
1*
#1100
0*
#1105
b1101110 D
b100 @
1*
#1110
0*
#1115
b1101111 D
b100 @
1*
#1120
0*
#1125
b1110000 D
b100 @
1*
#1130
0*
#1135
b1110001 D
b100 @
1*
#1140
0*
#1145
b1110010 D
b100 @
1*
#1150
0*
#1155
b1110011 D
b100 @
1*
#1160
0*
#1165
b1110100 D
b100 @
1*
#1170
0*
#1175
b1110101 D
b100 @
1*
#1180
0*
#1185
b1110110 D
b100 @
1*
#1190
0*
#1195
b1110111 D
b100 @
1*
#1200
0*
#1205
b1111000 D
b100 @
1*
#1210
0*
#1215
b1111001 D
b100 @
1*
#1220
0*
#1225
b1111010 D
b100 @
1*
#1230
0*
#1235
b1111011 D
b100 @
1*
#1240
0*
#1245
b1111100 D
b100 @
1*
#1250
0*
#1255
b1111101 D
b100 @
1*
#1260
0*
#1265
b1111110 D
b100 @
1*
#1270
0*
#1275
b1111111 D
b100 @
1*
#1280
0*
#1285
b10000000 D
b100 @
1*
